ffsjs.py
ffsjs-1.0.0.dist-info/DESCRIPTION.rst
ffsjs-1.0.0.dist-info/METADATA
ffsjs-1.0.0.dist-info/RECORD
ffsjs-1.0.0.dist-info/WHEEL
ffsjs-1.0.0.dist-info/entry_points.txt
ffsjs-1.0.0.dist-info/metadata.json
ffsjs-1.0.0.dist-info/top_level.txt
