Metadata-Version: 2.0
Name: ffsjs
Version: 1.0.0
Summary: bare bones JavaScript package manager for web development
Home-page: https://github.com/trehn/ffsjs
Author: Torsten Rehn
Author-email: torsten@rehn.email
License: GPLv3
Keywords: cdn,cdnjs,css,downloader,javascript,manager,minified,mirror,package
Platform: UNKNOWN
Classifier: Development Status :: 5 - Production/Stable
Classifier: Environment :: Console
Classifier: Intended Audience :: Developers
Classifier: License :: OSI Approved :: GNU General Public License v3 (GPLv3)
Classifier: Natural Language :: English
Classifier: Operating System :: OS Independent
Classifier: Programming Language :: JavaScript
Classifier: Programming Language :: Python
Classifier: Programming Language :: Python :: 3.4
Classifier: Programming Language :: Python :: 3.5
Classifier: Programming Language :: Python :: 3.6
Classifier: Topic :: Internet :: WWW/HTTP
Classifier: Topic :: Software Development
Classifier: Topic :: Utilities
Requires-Python: >=3
Requires-Dist: requests
